sauce/__init__.py
sauce-1.4.dist-info/METADATA
sauce-1.4.dist-info/WHEEL
sauce-1.4.dist-info/top_level.txt
sauce-1.4.dist-info/RECORD
