Metadata-Version: 2.4
Name: sauce
Version: 1.4
Summary: SAUCE record parser
Home-page: https://github.com/tehmaze/sauce
Author: Wijnand Modderman-Lenstra
Author-email: maze@pyth0n.org
Dynamic: author
Dynamic: author-email
Dynamic: home-page
Dynamic: summary
